forte.huggingface-0.0.3-py3.7-nspkg.pth
fortex/huggingface/__init__.py
fortex/huggingface/bio_ner_predictor.py
fortex/huggingface/question_and_answering_multi.py
fortex/huggingface/question_and_answering_single.py
fortex/huggingface/token_classification.py
fortex/huggingface/transformers_processor.py
fortex/huggingface/zero_shot_classifier.py
forte.huggingface-0.0.3.dist-info/METADATA
forte.huggingface-0.0.3.dist-info/WHEEL
forte.huggingface-0.0.3.dist-info/namespace_packages.txt
forte.huggingface-0.0.3.dist-info/top_level.txt
forte.huggingface-0.0.3.dist-info/RECORD
